luvex/Linearregression.py
luvex/__init__.py
luvex/decisiontree.py
luvex/knn.py
luvex/logisticregression.py
luvex/multilinear.py
luvex/node.py
luvex/randomforest.py
luvex/svm.py
luvex/xgbclassifier.py
luvex/xgbclasstree.py
test/__init__.py
test/test_decisiontree.py
test/test_knn.py
test/test_linearregression.py
test/test_logisticregression.py
test/test_multilinear.py
test/test_randomforest.py
tests/__init__.py
tests/tempCodeRunnerFile.py
tests/test_decisiontree.py
tests/test_knn.py
tests/test_linearregression.py
tests/test_logisticregression.py
tests/test_multilinear.py
tests/test_randomforest.py
tests/test_svm.py
tests/test_xgbclassifier.py
luvex-0.1.17.dist-info/LICENSE
luvex-0.1.17.dist-info/METADATA
luvex-0.1.17.dist-info/WHEEL
luvex-0.1.17.dist-info/top_level.txt
luvex-0.1.17.dist-info/RECORD
