Metadata-Version: 2.1
Name: luvex
Version: 0.1.17
Summary: Regression - Linear(Least Squares Method), Multiple Linear . Classification - KNN, Logistic Regression, Decision Trees, Random Forests, SVM, XGBoost 
Home-page: https://github.com/Gladson-K/luvex
Author: Gladson K
Author-email: gladson1414@gmail.com
Classifier: Programming Language :: Python :: 3
Classifier: License :: OSI Approved :: MIT License
Classifier: Operating System :: OS Independent
Requires-Python: >=3.6
License-File: LICENSE
Requires-Dist: numpy
Requires-Dist: scikit-learn
